{
 "actions": [],
 "allow_rename": 1,
 "creation": "2024-02-04 16:08:48.733011",
 "doctype": "DocType",
 "editable_grid": 1,
 "engine": "InnoDB",
 "field_order": [
  "description",
  "done"
 ],
 "fields": [
  {
   "fieldname": "description",
   "fieldtype": "Small Text",
   "in_list_view": 1,
   "label": "Description",
   "reqd": 1
  },
  {
   "default": "0",
   "fieldname": "done",
   "fieldtype": "Check",
   "in_list_view": 1,
   "label": "Done"
  }
 ],
 "index_web_pages_for_search": 1,
 "istable": 1,
 "links": [],
 "modified": "2024-02-04 16:18:19.866133",
 "modified_by": "Administrator",
 "module": "Ptdc Av",
 "name": "Action Task",
 "owner": "Administrator",
 "permissions": [],
 "sort_field": "modified",
 "sort_order": "DESC",
 "states": []
}